qi_irida_utils/__init__.py
qi_irida_utils/cli.py
qi_irida_utils/irida_workflow.py
qi_irida_utils/workflow_helper.py
qi_irida_utils-0.1.2.dist-info/AUTHORS.md
qi_irida_utils-0.1.2.dist-info/LICENSE
qi_irida_utils-0.1.2.dist-info/METADATA
qi_irida_utils-0.1.2.dist-info/WHEEL
qi_irida_utils-0.1.2.dist-info/entry_points.txt
qi_irida_utils-0.1.2.dist-info/top_level.txt
qi_irida_utils-0.1.2.dist-info/RECORD
