Metadata-Version: 2.1
Name: qi-irida-utils
Version: 0.1.2
Summary: Helper scripts for working with IRIDA
Home-page: https://github.com/happykhan/qi_irida_utils
Author: Nabil-Fareed Alikhan
Author-email: nabil-fareed.alikhan@quadram.ac.uk
License: GNU General Public License v3
Keywords: qi_irida_utils
Platform: UNKNOWN
Classifier: Development Status :: 2 - Pre-Alpha
Classifier: Intended Audience :: Developers
Classifier: License :: OSI Approved :: GNU General Public License v3 (GPLv3)
Classifier: Natural Language :: English
Classifier: Programming Language :: Python :: 3.5
Classifier: Programming Language :: Python :: 3.6
Classifier: Programming Language :: Python :: 3.7
Requires-Dist: Click (>=6.0)
